<tokens>
<keyword> class </keyword>
<identifier> MarketMaker </identifier>
<symbol> { </symbol>
<keyword> field </keyword>
<keyword> int </keyword>
<identifier> position </identifier>
<symbol> ; </symbol>
<keyword> field </keyword>
<keyword> int </keyword>
<identifier> avgEntryPrice </identifier>
<symbol> ; </symbol>
<keyword> field </keyword>
<keyword> int </keyword>
<identifier> realizedPnL </identifier>
<symbol> ; </symbol>
<keyword> field </keyword>
<keyword> int </keyword>
<identifier> bidPrice </identifier>
<symbol> ; </symbol>
<keyword> field </keyword>
<keyword> int </keyword>
<identifier> askPrice </identifier>
<symbol> ; </symbol>
<keyword> field </keyword>
<keyword> int </keyword>
<identifier> quoteSize </identifier>
<symbol> ; </symbol>
<keyword> field </keyword>
<keyword> int </keyword>
<identifier> spreadWidth </identifier>
<symbol> ; </symbol>
<keyword> field </keyword>
<keyword> int </keyword>
<identifier> totalFills </identifier>
<symbol> ; </symbol>
<keyword> field </keyword>
<keyword> int </keyword>
<identifier> maxPosition </identifier>
<symbol> ; </symbol>
<keyword> static </keyword>
<keyword> int </keyword>
<identifier> SPREAD_TICK </identifier>
<symbol> ; </symbol>
<keyword> static </keyword>
<keyword> int </keyword>
<identifier> MAX_SPREAD </identifier>
<symbol> ; </symbol>
<keyword> static </keyword>
<keyword> int </keyword>
<identifier> MIN_SPREAD </identifier>
<symbol> ; </symbol>
<keyword> static </keyword>
<keyword> int </keyword>
<identifier> MAX_QUOTE_SIZE </identifier>
<symbol> ; </symbol>
<keyword> static </keyword>
<keyword> int </keyword>
<identifier> MIN_QUOTE_SIZE </identifier>
<symbol> ; </symbol>
<keyword> constructor </keyword>
<identifier> MarketMaker </identifier>
<identifier> new </identifier>
<symbol> ( </symbol>
<keyword> int </keyword>
<identifier> initSpread </identifier>
<symbol> , </symbol>
<keyword> int </keyword>
<identifier> initSize </identifier>
<symbol> , </symbol>
<keyword> int </keyword>
<identifier> posLimit </identifier>
<symbol> ) </symbol>
<symbol> { </symbol>
<keyword> let </keyword>
<identifier> SPREAD_TICK </identifier>
<symbol> = </symbol>
<integerConstant> 5 </integerConstant>
<symbol> ; </symbol>
<keyword> let </keyword>
<identifier> MAX_SPREAD </identifier>
<symbol> = </symbol>
<integerConstant> 50 </integerConstant>
<symbol> ; </symbol>
<keyword> let </keyword>
<identifier> MIN_SPREAD </identifier>
<symbol> = </symbol>
<integerConstant> 5 </integerConstant>
<symbol> ; </symbol>
<keyword> let </keyword>
<identifier> MAX_QUOTE_SIZE </identifier>
<symbol> = </symbol>
<integerConstant> 10 </integerConstant>
<symbol> ; </symbol>
<keyword> let </keyword>
<identifier> MIN_QUOTE_SIZE </identifier>
<symbol> = </symbol>
<integerConstant> 1 </integerConstant>
<symbol> ; </symbol>
<keyword> let </keyword>
<identifier> position </identifier>
<symbol> = </symbol>
<integerConstant> 0 </integerConstant>
<symbol> ; </symbol>
<keyword> let </keyword>
<identifier> avgEntryPrice </identifier>
<symbol> = </symbol>
<integerConstant> 0 </integerConstant>
<symbol> ; </symbol>
<keyword> let </keyword>
<identifier> realizedPnL </identifier>
<symbol> = </symbol>
<integerConstant> 0 </integerConstant>
<symbol> ; </symbol>
<keyword> let </keyword>
<identifier> bidPrice </identifier>
<symbol> = </symbol>
<integerConstant> 0 </integerConstant>
<symbol> ; </symbol>
<keyword> let </keyword>
<identifier> askPrice </identifier>
<symbol> = </symbol>
<integerConstant> 0 </integerConstant>
<symbol> ; </symbol>
<keyword> let </keyword>
<identifier> quoteSize </identifier>
<symbol> = </symbol>
<identifier> initSize </identifier>
<symbol> ; </symbol>
<keyword> let </keyword>
<identifier> spreadWidth </identifier>
<symbol> = </symbol>
<identifier> initSpread </identifier>
<symbol> ; </symbol>
<keyword> let </keyword>
<identifier> totalFills </identifier>
<symbol> = </symbol>
<integerConstant> 0 </integerConstant>
<symbol> ; </symbol>
<keyword> let </keyword>
<identifier> maxPosition </identifier>
<symbol> = </symbol>
<identifier> posLimit </identifier>
<symbol> ; </symbol>
<keyword> return </keyword>
<keyword> this </keyword>
<symbol> ; </symbol>
<symbol> } </symbol>
<keyword> method </keyword>
<keyword> void </keyword>
<identifier> dispose </identifier>
<symbol> ( </symbol>
<symbol> ) </symbol>
<symbol> { </symbol>
<keyword> do </keyword>
<identifier> Memory </identifier>
<symbol> . </symbol>
<identifier> deAlloc </identifier>
<symbol> ( </symbol>
<keyword> this </keyword>
<symbol> ) </symbol>
<symbol> ; </symbol>
<keyword> return </keyword>
<symbol> ; </symbol>
<symbol> } </symbol>
<keyword> method </keyword>
<keyword> void </keyword>
<identifier> updateQuotes </identifier>
<symbol> ( </symbol>
<keyword> int </keyword>
<identifier> midPrice </identifier>
<symbol> ) </symbol>
<symbol> { </symbol>
<keyword> let </keyword>
<identifier> bidPrice </identifier>
<symbol> = </symbol>
<identifier> midPrice </identifier>
<symbol> - </symbol>
<identifier> spreadWidth </identifier>
<symbol> ; </symbol>
<keyword> let </keyword>
<identifier> askPrice </identifier>
<symbol> = </symbol>
<identifier> midPrice </identifier>
<symbol> + </symbol>
<identifier> spreadWidth </identifier>
<symbol> ; </symbol>
<keyword> if </keyword>
<symbol> ( </symbol>
<identifier> bidPrice </identifier>
<symbol> &lt; </symbol>
<integerConstant> 0 </integerConstant>
<symbol> ) </symbol>
<symbol> { </symbol>
<keyword> let </keyword>
<identifier> bidPrice </identifier>
<symbol> = </symbol>
<integerConstant> 0 </integerConstant>
<symbol> ; </symbol>
<symbol> } </symbol>
<keyword> return </keyword>
<symbol> ; </symbol>
<symbol> } </symbol>
<keyword> method </keyword>
<keyword> void </keyword>
<identifier> onFill </identifier>
<symbol> ( </symbol>
<keyword> int </keyword>
<identifier> price </identifier>
<symbol> , </symbol>
<keyword> int </keyword>
<identifier> qty </identifier>
<symbol> , </symbol>
<keyword> boolean </keyword>
<identifier> isBuy </identifier>
<symbol> ) </symbol>
<symbol> { </symbol>
<keyword> var </keyword>
<keyword> int </keyword>
<identifier> tradeValue </identifier>
<symbol> ; </symbol>
<keyword> var </keyword>
<keyword> int </keyword>
<identifier> prevPosition </identifier>
<symbol> ; </symbol>
<keyword> let </keyword>
<identifier> totalFills </identifier>
<symbol> = </symbol>
<identifier> totalFills </identifier>
<symbol> + </symbol>
<integerConstant> 1 </integerConstant>
<symbol> ; </symbol>
<keyword> let </keyword>
<identifier> prevPosition </identifier>
<symbol> = </symbol>
<identifier> position </identifier>
<symbol> ; </symbol>
<keyword> if </keyword>
<symbol> ( </symbol>
<identifier> isBuy </identifier>
<symbol> ) </symbol>
<symbol> { </symbol>
<keyword> if </keyword>
<symbol> ( </symbol>
<identifier> position </identifier>
<symbol> &lt; </symbol>
<integerConstant> 0 </integerConstant>
<symbol> ) </symbol>
<symbol> { </symbol>
<keyword> if </keyword>
<symbol> ( </symbol>
<identifier> qty </identifier>
<symbol> &gt; </symbol>
<symbol> ( </symbol>
<symbol> - </symbol>
<identifier> position </identifier>
<symbol> ) </symbol>
<symbol> ) </symbol>
<symbol> { </symbol>
<keyword> let </keyword>
<identifier> realizedPnL </identifier>
<symbol> = </symbol>
<identifier> realizedPnL </identifier>
<symbol> + </symbol>
<symbol> ( </symbol>
<symbol> ( </symbol>
<symbol> - </symbol>
<identifier> position </identifier>
<symbol> ) </symbol>
<symbol> * </symbol>
<symbol> ( </symbol>
<identifier> avgEntryPrice </identifier>
<symbol> - </symbol>
<identifier> price </identifier>
<symbol> ) </symbol>
<symbol> / </symbol>
<integerConstant> 10 </integerConstant>
<symbol> ) </symbol>
<symbol> ; </symbol>
<keyword> let </keyword>
<identifier> avgEntryPrice </identifier>
<symbol> = </symbol>
<identifier> price </identifier>
<symbol> ; </symbol>
<keyword> let </keyword>
<identifier> position </identifier>
<symbol> = </symbol>
<identifier> position </identifier>
<symbol> + </symbol>
<identifier> qty </identifier>
<symbol> ; </symbol>
<symbol> } </symbol>
<keyword> else </keyword>
<symbol> { </symbol>
<keyword> let </keyword>
<identifier> realizedPnL </identifier>
<symbol> = </symbol>
<identifier> realizedPnL </identifier>
<symbol> + </symbol>
<symbol> ( </symbol>
<identifier> qty </identifier>
<symbol> * </symbol>
<symbol> ( </symbol>
<identifier> avgEntryPrice </identifier>
<symbol> - </symbol>
<identifier> price </identifier>
<symbol> ) </symbol>
<symbol> / </symbol>
<integerConstant> 10 </integerConstant>
<symbol> ) </symbol>
<symbol> ; </symbol>
<keyword> let </keyword>
<identifier> position </identifier>
<symbol> = </symbol>
<identifier> position </identifier>
<symbol> + </symbol>
<identifier> qty </identifier>
<symbol> ; </symbol>
<keyword> if </keyword>
<symbol> ( </symbol>
<identifier> position </identifier>
<symbol> = </symbol>
<integerConstant> 0 </integerConstant>
<symbol> ) </symbol>
<symbol> { </symbol>
<keyword> let </keyword>
<identifier> avgEntryPrice </identifier>
<symbol> = </symbol>
<integerConstant> 0 </integerConstant>
<symbol> ; </symbol>
<symbol> } </symbol>
<symbol> } </symbol>
<symbol> } </symbol>
<keyword> else </keyword>
<symbol> { </symbol>
<keyword> if </keyword>
<symbol> ( </symbol>
<identifier> position </identifier>
<symbol> = </symbol>
<integerConstant> 0 </integerConstant>
<symbol> ) </symbol>
<symbol> { </symbol>
<keyword> let </keyword>
<identifier> avgEntryPrice </identifier>
<symbol> = </symbol>
<identifier> price </identifier>
<symbol> ; </symbol>
<symbol> } </symbol>
<keyword> else </keyword>
<symbol> { </symbol>
<keyword> let </keyword>
<identifier> avgEntryPrice </identifier>
<symbol> = </symbol>
<symbol> ( </symbol>
<symbol> ( </symbol>
<identifier> position </identifier>
<symbol> * </symbol>
<identifier> avgEntryPrice </identifier>
<symbol> ) </symbol>
<symbol> + </symbol>
<symbol> ( </symbol>
<identifier> qty </identifier>
<symbol> * </symbol>
<identifier> price </identifier>
<symbol> ) </symbol>
<symbol> ) </symbol>
<symbol> / </symbol>
<symbol> ( </symbol>
<identifier> position </identifier>
<symbol> + </symbol>
<identifier> qty </identifier>
<symbol> ) </symbol>
<symbol> ; </symbol>
<symbol> } </symbol>
<keyword> let </keyword>
<identifier> position </identifier>
<symbol> = </symbol>
<identifier> position </identifier>
<symbol> + </symbol>
<identifier> qty </identifier>
<symbol> ; </symbol>
<symbol> } </symbol>
<symbol> } </symbol>
<keyword> else </keyword>
<symbol> { </symbol>
<keyword> if </keyword>
<symbol> ( </symbol>
<identifier> position </identifier>
<symbol> &gt; </symbol>
<integerConstant> 0 </integerConstant>
<symbol> ) </symbol>
<symbol> { </symbol>
<keyword> if </keyword>
<symbol> ( </symbol>
<identifier> qty </identifier>
<symbol> &gt; </symbol>
<identifier> position </identifier>
<symbol> ) </symbol>
<symbol> { </symbol>
<keyword> let </keyword>
<identifier> realizedPnL </identifier>
<symbol> = </symbol>
<identifier> realizedPnL </identifier>
<symbol> + </symbol>
<symbol> ( </symbol>
<identifier> position </identifier>
<symbol> * </symbol>
<symbol> ( </symbol>
<identifier> price </identifier>
<symbol> - </symbol>
<identifier> avgEntryPrice </identifier>
<symbol> ) </symbol>
<symbol> / </symbol>
<integerConstant> 10 </integerConstant>
<symbol> ) </symbol>
<symbol> ; </symbol>
<keyword> let </keyword>
<identifier> avgEntryPrice </identifier>
<symbol> = </symbol>
<identifier> price </identifier>
<symbol> ; </symbol>
<keyword> let </keyword>
<identifier> position </identifier>
<symbol> = </symbol>
<identifier> position </identifier>
<symbol> - </symbol>
<identifier> qty </identifier>
<symbol> ; </symbol>
<symbol> } </symbol>
<keyword> else </keyword>
<symbol> { </symbol>
<keyword> let </keyword>
<identifier> realizedPnL </identifier>
<symbol> = </symbol>
<identifier> realizedPnL </identifier>
<symbol> + </symbol>
<symbol> ( </symbol>
<identifier> qty </identifier>
<symbol> * </symbol>
<symbol> ( </symbol>
<identifier> price </identifier>
<symbol> - </symbol>
<identifier> avgEntryPrice </identifier>
<symbol> ) </symbol>
<symbol> / </symbol>
<integerConstant> 10 </integerConstant>
<symbol> ) </symbol>
<symbol> ; </symbol>
<keyword> let </keyword>
<identifier> position </identifier>
<symbol> = </symbol>
<identifier> position </identifier>
<symbol> - </symbol>
<identifier> qty </identifier>
<symbol> ; </symbol>
<keyword> if </keyword>
<symbol> ( </symbol>
<identifier> position </identifier>
<symbol> = </symbol>
<integerConstant> 0 </integerConstant>
<symbol> ) </symbol>
<symbol> { </symbol>
<keyword> let </keyword>
<identifier> avgEntryPrice </identifier>
<symbol> = </symbol>
<integerConstant> 0 </integerConstant>
<symbol> ; </symbol>
<symbol> } </symbol>
<symbol> } </symbol>
<symbol> } </symbol>
<keyword> else </keyword>
<symbol> { </symbol>
<keyword> if </keyword>
<symbol> ( </symbol>
<identifier> position </identifier>
<symbol> = </symbol>
<integerConstant> 0 </integerConstant>
<symbol> ) </symbol>
<symbol> { </symbol>
<keyword> let </keyword>
<identifier> avgEntryPrice </identifier>
<symbol> = </symbol>
<identifier> price </identifier>
<symbol> ; </symbol>
<symbol> } </symbol>
<keyword> else </keyword>
<symbol> { </symbol>
<keyword> let </keyword>
<identifier> avgEntryPrice </identifier>
<symbol> = </symbol>
<symbol> ( </symbol>
<symbol> ( </symbol>
<symbol> ( </symbol>
<symbol> - </symbol>
<identifier> position </identifier>
<symbol> ) </symbol>
<symbol> * </symbol>
<identifier> avgEntryPrice </identifier>
<symbol> ) </symbol>
<symbol> + </symbol>
<symbol> ( </symbol>
<identifier> qty </identifier>
<symbol> * </symbol>
<identifier> price </identifier>
<symbol> ) </symbol>
<symbol> ) </symbol>
<symbol> / </symbol>
<symbol> ( </symbol>
<symbol> ( </symbol>
<symbol> - </symbol>
<identifier> position </identifier>
<symbol> ) </symbol>
<symbol> + </symbol>
<identifier> qty </identifier>
<symbol> ) </symbol>
<symbol> ; </symbol>
<symbol> } </symbol>
<keyword> let </keyword>
<identifier> position </identifier>
<symbol> = </symbol>
<identifier> position </identifier>
<symbol> - </symbol>
<identifier> qty </identifier>
<symbol> ; </symbol>
<symbol> } </symbol>
<symbol> } </symbol>
<keyword> return </keyword>
<symbol> ; </symbol>
<symbol> } </symbol>
<keyword> method </keyword>
<keyword> void </keyword>
<identifier> widenSpread </identifier>
<symbol> ( </symbol>
<symbol> ) </symbol>
<symbol> { </symbol>
<keyword> let </keyword>
<identifier> spreadWidth </identifier>
<symbol> = </symbol>
<identifier> spreadWidth </identifier>
<symbol> + </symbol>
<identifier> SPREAD_TICK </identifier>
<symbol> ; </symbol>
<keyword> if </keyword>
<symbol> ( </symbol>
<identifier> spreadWidth </identifier>
<symbol> &gt; </symbol>
<identifier> MAX_SPREAD </identifier>
<symbol> ) </symbol>
<symbol> { </symbol>
<keyword> let </keyword>
<identifier> spreadWidth </identifier>
<symbol> = </symbol>
<identifier> MAX_SPREAD </identifier>
<symbol> ; </symbol>
<symbol> } </symbol>
<keyword> return </keyword>
<symbol> ; </symbol>
<symbol> } </symbol>
<keyword> method </keyword>
<keyword> void </keyword>
<identifier> narrowSpread </identifier>
<symbol> ( </symbol>
<symbol> ) </symbol>
<symbol> { </symbol>
<keyword> let </keyword>
<identifier> spreadWidth </identifier>
<symbol> = </symbol>
<identifier> spreadWidth </identifier>
<symbol> - </symbol>
<identifier> SPREAD_TICK </identifier>
<symbol> ; </symbol>
<keyword> if </keyword>
<symbol> ( </symbol>
<identifier> spreadWidth </identifier>
<symbol> &lt; </symbol>
<identifier> MIN_SPREAD </identifier>
<symbol> ) </symbol>
<symbol> { </symbol>
<keyword> let </keyword>
<identifier> spreadWidth </identifier>
<symbol> = </symbol>
<identifier> MIN_SPREAD </identifier>
<symbol> ; </symbol>
<symbol> } </symbol>
<keyword> return </keyword>
<symbol> ; </symbol>
<symbol> } </symbol>
<keyword> method </keyword>
<keyword> void </keyword>
<identifier> increaseSize </identifier>
<symbol> ( </symbol>
<symbol> ) </symbol>
<symbol> { </symbol>
<keyword> let </keyword>
<identifier> quoteSize </identifier>
<symbol> = </symbol>
<identifier> quoteSize </identifier>
<symbol> + </symbol>
<integerConstant> 1 </integerConstant>
<symbol> ; </symbol>
<keyword> if </keyword>
<symbol> ( </symbol>
<identifier> quoteSize </identifier>
<symbol> &gt; </symbol>
<identifier> MAX_QUOTE_SIZE </identifier>
<symbol> ) </symbol>
<symbol> { </symbol>
<keyword> let </keyword>
<identifier> quoteSize </identifier>
<symbol> = </symbol>
<identifier> MAX_QUOTE_SIZE </identifier>
<symbol> ; </symbol>
<symbol> } </symbol>
<keyword> return </keyword>
<symbol> ; </symbol>
<symbol> } </symbol>
<keyword> method </keyword>
<keyword> void </keyword>
<identifier> decreaseSize </identifier>
<symbol> ( </symbol>
<symbol> ) </symbol>
<symbol> { </symbol>
<keyword> let </keyword>
<identifier> quoteSize </identifier>
<symbol> = </symbol>
<identifier> quoteSize </identifier>
<symbol> - </symbol>
<integerConstant> 1 </integerConstant>
<symbol> ; </symbol>
<keyword> if </keyword>
<symbol> ( </symbol>
<identifier> quoteSize </identifier>
<symbol> &lt; </symbol>
<identifier> MIN_QUOTE_SIZE </identifier>
<symbol> ) </symbol>
<symbol> { </symbol>
<keyword> let </keyword>
<identifier> quoteSize </identifier>
<symbol> = </symbol>
<identifier> MIN_QUOTE_SIZE </identifier>
<symbol> ; </symbol>
<symbol> } </symbol>
<keyword> return </keyword>
<symbol> ; </symbol>
<symbol> } </symbol>
<keyword> method </keyword>
<keyword> int </keyword>
<identifier> getUnrealizedPnL </identifier>
<symbol> ( </symbol>
<keyword> int </keyword>
<identifier> currentPrice </identifier>
<symbol> ) </symbol>
<symbol> { </symbol>
<keyword> if </keyword>
<symbol> ( </symbol>
<identifier> position </identifier>
<symbol> = </symbol>
<integerConstant> 0 </integerConstant>
<symbol> ) </symbol>
<symbol> { </symbol>
<keyword> return </keyword>
<integerConstant> 0 </integerConstant>
<symbol> ; </symbol>
<symbol> } </symbol>
<keyword> if </keyword>
<symbol> ( </symbol>
<identifier> position </identifier>
<symbol> &gt; </symbol>
<integerConstant> 0 </integerConstant>
<symbol> ) </symbol>
<symbol> { </symbol>
<keyword> return </keyword>
<symbol> ( </symbol>
<identifier> position </identifier>
<symbol> * </symbol>
<symbol> ( </symbol>
<identifier> currentPrice </identifier>
<symbol> - </symbol>
<identifier> avgEntryPrice </identifier>
<symbol> ) </symbol>
<symbol> ) </symbol>
<symbol> / </symbol>
<integerConstant> 10 </integerConstant>
<symbol> ; </symbol>
<symbol> } </symbol>
<keyword> return </keyword>
<symbol> ( </symbol>
<symbol> ( </symbol>
<symbol> - </symbol>
<identifier> position </identifier>
<symbol> ) </symbol>
<symbol> * </symbol>
<symbol> ( </symbol>
<identifier> avgEntryPrice </identifier>
<symbol> - </symbol>
<identifier> currentPrice </identifier>
<symbol> ) </symbol>
<symbol> ) </symbol>
<symbol> / </symbol>
<integerConstant> 10 </integerConstant>
<symbol> ; </symbol>
<symbol> } </symbol>
<keyword> method </keyword>
<keyword> int </keyword>
<identifier> getTotalPnL </identifier>
<symbol> ( </symbol>
<keyword> int </keyword>
<identifier> currentPrice </identifier>
<symbol> ) </symbol>
<symbol> { </symbol>
<keyword> return </keyword>
<identifier> realizedPnL </identifier>
<symbol> + </symbol>
<identifier> getUnrealizedPnL </identifier>
<symbol> ( </symbol>
<identifier> currentPrice </identifier>
<symbol> ) </symbol>
<symbol> ; </symbol>
<symbol> } </symbol>
<keyword> method </keyword>
<keyword> boolean </keyword>
<identifier> isOverLimit </identifier>
<symbol> ( </symbol>
<symbol> ) </symbol>
<symbol> { </symbol>
<keyword> if </keyword>
<symbol> ( </symbol>
<identifier> position </identifier>
<symbol> &gt; </symbol>
<identifier> maxPosition </identifier>
<symbol> ) </symbol>
<symbol> { </symbol>
<keyword> return </keyword>
<keyword> true </keyword>
<symbol> ; </symbol>
<symbol> } </symbol>
<keyword> if </keyword>
<symbol> ( </symbol>
<identifier> position </identifier>
<symbol> &lt; </symbol>
<symbol> ( </symbol>
<symbol> - </symbol>
<identifier> maxPosition </identifier>
<symbol> ) </symbol>
<symbol> ) </symbol>
<symbol> { </symbol>
<keyword> return </keyword>
<keyword> true </keyword>
<symbol> ; </symbol>
<symbol> } </symbol>
<keyword> return </keyword>
<keyword> false </keyword>
<symbol> ; </symbol>
<symbol> } </symbol>
<keyword> method </keyword>
<keyword> int </keyword>
<identifier> getPosition </identifier>
<symbol> ( </symbol>
<symbol> ) </symbol>
<symbol> { </symbol>
<keyword> return </keyword>
<identifier> position </identifier>
<symbol> ; </symbol>
<symbol> } </symbol>
<keyword> method </keyword>
<keyword> int </keyword>
<identifier> getAvgEntryPrice </identifier>
<symbol> ( </symbol>
<symbol> ) </symbol>
<symbol> { </symbol>
<keyword> return </keyword>
<identifier> avgEntryPrice </identifier>
<symbol> ; </symbol>
<symbol> } </symbol>
<keyword> method </keyword>
<keyword> int </keyword>
<identifier> getRealizedPnL </identifier>
<symbol> ( </symbol>
<symbol> ) </symbol>
<symbol> { </symbol>
<keyword> return </keyword>
<identifier> realizedPnL </identifier>
<symbol> ; </symbol>
<symbol> } </symbol>
<keyword> method </keyword>
<keyword> int </keyword>
<identifier> getBidPrice </identifier>
<symbol> ( </symbol>
<symbol> ) </symbol>
<symbol> { </symbol>
<keyword> return </keyword>
<identifier> bidPrice </identifier>
<symbol> ; </symbol>
<symbol> } </symbol>
<keyword> method </keyword>
<keyword> int </keyword>
<identifier> getAskPrice </identifier>
<symbol> ( </symbol>
<symbol> ) </symbol>
<symbol> { </symbol>
<keyword> return </keyword>
<identifier> askPrice </identifier>
<symbol> ; </symbol>
<symbol> } </symbol>
<keyword> method </keyword>
<keyword> int </keyword>
<identifier> getQuoteSize </identifier>
<symbol> ( </symbol>
<symbol> ) </symbol>
<symbol> { </symbol>
<keyword> return </keyword>
<identifier> quoteSize </identifier>
<symbol> ; </symbol>
<symbol> } </symbol>
<keyword> method </keyword>
<keyword> int </keyword>
<identifier> getSpreadWidth </identifier>
<symbol> ( </symbol>
<symbol> ) </symbol>
<symbol> { </symbol>
<keyword> return </keyword>
<identifier> spreadWidth </identifier>
<symbol> ; </symbol>
<symbol> } </symbol>
<keyword> method </keyword>
<keyword> int </keyword>
<identifier> getTotalFills </identifier>
<symbol> ( </symbol>
<symbol> ) </symbol>
<symbol> { </symbol>
<keyword> return </keyword>
<identifier> totalFills </identifier>
<symbol> ; </symbol>
<symbol> } </symbol>
<symbol> } </symbol>
</tokens>
